peeauto/__init__.py
peeauto-0.1.dist-info/LICENSE
peeauto-0.1.dist-info/METADATA
peeauto-0.1.dist-info/WHEEL
peeauto-0.1.dist-info/top_level.txt
peeauto-0.1.dist-info/RECORD
