Metadata-Version: 2.1
Name: peeauto
Version: 0.1
Summary: Automatic CRUD model framework
Home-page: https://github.com/fybmain/peeauto
Author: fyb
Author-email: fybmain@gmail.com
License: MIT License
Platform: all
Classifier: Operating System :: OS Independent
Classifier: Intended Audience :: Developers
Classifier: License :: OSI Approved :: MIT License
Classifier: Programming Language :: Python
Classifier: Programming Language :: Python :: 3
Classifier: Topic :: Software Development :: Libraries
Requires-Dist: peewee (>=3.9.3)
